<?xml version = '1.0' encoding = 'UTF-8'?>
<Diagram class="oracle.dbtools.crest.swingui.relational.DPVRelational" name="Relational_1" id="30DEE33B-6E22-C492-E3D1-FA1633D905A9">
<createdBy>Dubster</createdBy>
<modifiedBy>Dubster</modifiedBy>
<createdTime>2024-02-18 22:00:36 UTC</createdTime>
<autoRoute>false</autoRoute>
<boxInbox>true</boxInbox>
<showLegend>false</showLegend>
<showLabels>false</showLabels>
<showRelAttributes>false</showRelAttributes>
<gridEnabled>false</gridEnabled>
<showGrid>false</showGrid>
<diagramColor>-1</diagramColor>
<display>false</display>
<notation>1</notation>
<objectViews>
<OView class="oracle.dbtools.crest.swingui.relational.TVTable" oid="014D8FA2-258F-AB11-1808-615C3C126159" otype="Table" vid="32A3A317-1E6C-C525-77E8-4E4845D23657">
<hideElementsInCurrentOnly>false</hideElementsInCurrentOnly>
<bounds x="313" y="16" width="170" height="110"/>
</OView>
<OView class="oracle.dbtools.crest.swingui.relational.TVTable" oid="07CD579D-6C4D-FFD0-841A-C0248FAF0C01" otype="Table" vid="411C5987-D5BC-63FA-1841-B507AF1391A9">
<hideElementsInCurrentOnly>false</hideElementsInCurrentOnly>
<bounds x="548" y="234" width="170" height="138"/>
</OView>
<OView class="oracle.dbtools.crest.swingui.relational.TVTable" oid="0EC0EBD5-BCE5-9716-2B17-D555B9DD91E9" otype="Table" vid="0E47DEED-DBD2-B045-FF46-C83CF2446E86">
<hideElementsInCurrentOnly>false</hideElementsInCurrentOnly>
<bounds x="19" y="12" width="245" height="156"/>
</OView>
<OView class="oracle.dbtools.crest.swingui.relational.TVTable" oid="655AD767-A016-38B2-5FCE-4090D4173163" otype="Table" vid="0C066366-8117-6782-F2E1-54D61DB7A4C5">
<hideElementsInCurrentOnly>false</hideElementsInCurrentOnly>
<bounds x="275" y="237" width="170" height="110"/>
</OView>
<OView class="oracle.dbtools.crest.swingui.relational.TVTable" oid="7318FFF3-6333-350D-43D4-17EA6EE51487" otype="Table" vid="A1832A5C-5285-D0C9-7B5F-952224F3F29B">
<hideElementsInCurrentOnly>false</hideElementsInCurrentOnly>
<bounds x="28" y="237" width="170" height="160"/>
</OView>
<OView class="oracle.dbtools.crest.swingui.relational.TVTable" oid="A45BF64B-D2CF-73AE-0F8E-5702F7CA2D21" otype="Table" vid="05CF29DD-1A00-3475-A2FB-0894D26D6DB0">
<hideElementsInCurrentOnly>false</hideElementsInCurrentOnly>
<bounds x="539" y="18" width="170" height="110"/>
</OView>
<OView class="oracle.dbtools.crest.swingui.relational.TVTable" oid="A79188E2-EE4A-CB8C-54BB-8049534F6365" otype="Table" vid="6D777819-6132-6FF2-8D99-DDF02E7C4FE6">
<hideElementsInCurrentOnly>false</hideElementsInCurrentOnly>
<bounds x="283" y="424" width="170" height="110"/>
</OView>
<OView class="oracle.dbtools.crest.swingui.relational.TVTable" oid="B70181FC-FE28-22CC-16B5-9A5C706E831B" otype="Table" vid="E745DABA-1BFE-D504-CD68-987027D9F346">
<hideElementsInCurrentOnly>false</hideElementsInCurrentOnly>
<bounds x="29" y="427" width="168" height="110"/>
</OView>
</objectViews>
<connectors>
<Connector class="oracle.dbtools.crest.swingui.relational.TVFKRelation" oid="01C9E1CB-D250-EC73-3E50-3837FC6D1720" otype="FKIndexAssociation" vid_source="E745DABA-1BFE-D504-CD68-987027D9F346" vid_target="6D777819-6132-6FF2-8D99-DDF02E7C4FE6">
<hideElementsInCurrentOnly>false</hideElementsInCurrentOnly>
<backgroundColor>-16777216</backgroundColor>
<lineWidth>1</lineWidth>
<points>
<point x="197" y="480"/>
<point x="283" y="480"/>
</points>
</Connector>
<Connector class="oracle.dbtools.crest.swingui.relational.TVFKRelation" oid="03DB3443-591E-BC45-176C-EA47DC559F52" otype="FKIndexAssociation" vid_source="32A3A317-1E6C-C525-77E8-4E4845D23657" vid_target="0E47DEED-DBD2-B045-FF46-C83CF2446E86">
<hideElementsInCurrentOnly>false</hideElementsInCurrentOnly>
<backgroundColor>-16777216</backgroundColor>
<lineWidth>1</lineWidth>
<points>
<point x="313" y="71"/>
<point x="264" y="71"/>
</points>
</Connector>
<Connector class="oracle.dbtools.crest.swingui.relational.TVFKRelation" oid="0574980F-93B2-AE8B-C4AF-546064F18D53" otype="FKIndexAssociation" vid_source="32A3A317-1E6C-C525-77E8-4E4845D23657" vid_target="05CF29DD-1A00-3475-A2FB-0894D26D6DB0">
<hideElementsInCurrentOnly>false</hideElementsInCurrentOnly>
<backgroundColor>-16777216</backgroundColor>
<lineWidth>1</lineWidth>
<points>
<point x="483" y="72"/>
<point x="539" y="72"/>
</points>
</Connector>
<Connector class="oracle.dbtools.crest.swingui.relational.TVFKRelation" oid="42B0A90C-A7AA-4033-3F67-993884789399" otype="FKIndexAssociation" vid_source="411C5987-D5BC-63FA-1841-B507AF1391A9" vid_target="05CF29DD-1A00-3475-A2FB-0894D26D6DB0">
<hideElementsInCurrentOnly>false</hideElementsInCurrentOnly>
<backgroundColor>-16777216</backgroundColor>
<lineWidth>1</lineWidth>
<points>
<point x="628" y="234"/>
<point x="628" y="128"/>
</points>
</Connector>
<Connector class="oracle.dbtools.crest.swingui.relational.TVFKRelation" oid="94DD5FED-66D7-D35E-89D8-773CA80C86C7" otype="FKIndexAssociation" vid_source="0C066366-8117-6782-F2E1-54D61DB7A4C5" vid_target="A1832A5C-5285-D0C9-7B5F-952224F3F29B">
<hideElementsInCurrentOnly>false</hideElementsInCurrentOnly>
<backgroundColor>-16777216</backgroundColor>
<lineWidth>1</lineWidth>
<points>
<point x="275" y="292"/>
<point x="198" y="292"/>
</points>
</Connector>
<Connector class="oracle.dbtools.crest.swingui.relational.TVFKRelation" oid="D0D32AF3-08F9-7A51-F18D-3DC38C7FCB16" otype="FKIndexAssociation" vid_source="0C066366-8117-6782-F2E1-54D61DB7A4C5" vid_target="411C5987-D5BC-63FA-1841-B507AF1391A9">
<hideElementsInCurrentOnly>false</hideElementsInCurrentOnly>
<backgroundColor>-16777216</backgroundColor>
<lineWidth>1</lineWidth>
<points>
<point x="445" y="292"/>
<point x="548" y="292"/>
</points>
</Connector>
<Connector class="oracle.dbtools.crest.swingui.relational.TVFKRelation" oid="D1D9E43A-1D54-F0E4-3BB2-4EB06BF66018" otype="FKIndexAssociation" vid_source="0C066366-8117-6782-F2E1-54D61DB7A4C5" vid_target="6D777819-6132-6FF2-8D99-DDF02E7C4FE6">
<hideElementsInCurrentOnly>false</hideElementsInCurrentOnly>
<backgroundColor>-16777216</backgroundColor>
<lineWidth>1</lineWidth>
<points>
<point x="364" y="347"/>
<point x="364" y="424"/>
</points>
</Connector>
<Connector class="oracle.dbtools.crest.swingui.relational.TVFKRelation" oid="F0EF034D-998A-5BC2-9370-5CFCC5834E3B" otype="FKIndexAssociation" vid_source="0E47DEED-DBD2-B045-FF46-C83CF2446E86" vid_target="A1832A5C-5285-D0C9-7B5F-952224F3F29B">
<hideElementsInCurrentOnly>false</hideElementsInCurrentOnly>
<backgroundColor>-16777216</backgroundColor>
<lineWidth>1</lineWidth>
<points>
<point x="113" y="168"/>
<point x="113" y="237"/>
</points>
</Connector>
</connectors>
</Diagram>
